libex/__init__.py
libex/base_individual_listener.py
libex/base_individual_rest.py
libex/base_individual_ws.py
libex/base_market_listener.py
libex/base_market_ws.py
libex/const.py
libex/events.py
libex/fail_exception.py
libex/loader.py
libex/thread_pool.py
libex/common/__init__.py
libex/common/book.py
libex/common/rate.py
libex/common/timer.py
libex/exchanges/__init__.py
libex/exchanges/bitfinex/__init__.py
libex/exchanges/bitfinex/const.py
libex/exchanges/bitfinex/helper.py
libex/exchanges/bitfinex/individual_rest.py
libex/exchanges/bitfinex/individual_ws.py
libex/exchanges/bitfinex/market_rest.py
libex/exchanges/bitfinex/market_ws.py
libex/exchanges/bitfinex/native_ex.py
libex/exchanges/okex/__init__.py
libex/exchanges/okex/book.py
libex/exchanges/okex/code_converter.py
libex/exchanges/okex/const.py
libex/exchanges/okex/helper.py
libex/exchanges/okex/individual_rest.py
libex/exchanges/okex/individual_ws.py
libex/exchanges/okex/market_rest.py
libex/exchanges/okex/market_ws.py
libex/exchanges/okex/native_ex.py
libex/exchanges/okex/rates.py
libex/exchanges/okex/sdk/__init__.py
libex/exchanges/okex/sdk/account_api.py
libex/exchanges/okex/sdk/client.py
libex/exchanges/okex/sdk/consts.py
libex/exchanges/okex/sdk/ett_api.py
libex/exchanges/okex/sdk/exceptions.py
libex/exchanges/okex/sdk/futures_api.py
libex/exchanges/okex/sdk/lever_api.py
libex/exchanges/okex/sdk/spot_api.py
libex/exchanges/okex/sdk/swap_api.py
libex/exchanges/okex/sdk/utils.py
libex/exchanges/okex/sdk/websocket.py
libex-0.1.1.dist-info/LICENSE
libex-0.1.1.dist-info/METADATA
libex-0.1.1.dist-info/WHEEL
libex-0.1.1.dist-info/top_level.txt
libex-0.1.1.dist-info/RECORD
