Metadata-Version: 2.1
Name: libex
Version: 0.1.1
Summary: Crypto Currency Exchange Library
Home-page: https://gitlab.com/dozenc/libex
Author: dozenc
Author-email: dozenc@outlook.com
License: UNKNOWN
Project-URL: Bug Reports, https://gitlab.com/dozenc/libex
Project-URL: Funding, https://gitlab.com/dozenc/libex
Project-URL: Say Thanks!, https://gitlab.com/dozenc/libex
Project-URL: Source, https://gitlab.com/dozenc/libex
Platform: UNKNOWN
Classifier: Programming Language :: Python :: 3
Classifier: License :: OSI Approved :: MIT License
Classifier: Operating System :: OS Independent
Requires-Python: >=3.5, <4
Requires-Dist: requests (==2.22.0)
Requires-Dist: iso8601 (==0.1.12)
Requires-Dist: websockets (>=7.0)
Requires-Dist: python-dateutil (==2.8.0)
